copyrite/__init__.py
copyrite/alias.py
copyrite/cli.py
copyrite/copyrite.py
copyrite/vcs/__init__.py
copyrite/vcs/base.py
copyrite/vcs/git.py
copyrite-0.1.0.dist-info/DESCRIPTION.rst
copyrite-0.1.0.dist-info/METADATA
copyrite-0.1.0.dist-info/RECORD
copyrite-0.1.0.dist-info/WHEEL
copyrite-0.1.0.dist-info/entry_points.txt
copyrite-0.1.0.dist-info/metadata.json
copyrite-0.1.0.dist-info/top_level.txt
