Metadata-Version: 2.0
Name: copyrite
Version: 0.1.0
Summary: Updates copyright notices.
Home-page: https://github.com/PCManticore/copyrite
Author: Claudiu Popa
Author-email: pcmanticore@gmail.com
License: MIT license
Keywords: copyrite
Platform: UNKNOWN
Classifier: Development Status :: 2 - Pre-Alpha
Classifier: Intended Audience :: Developers
Classifier: License :: OSI Approved :: MIT License
Classifier: Natural Language :: English
Classifier: Programming Language :: Python :: 3.5
Requires-Dist: Click (>=6.0)
Requires-Dist: jsonschema
